{
  "project_info": {
    "project_number": "924784679303",
    "project_id": "musiclist-ad348",
    "storage_bucket": "musiclist-ad348.appspot.com"
  },
  "client": [
    {
      "client_info": {
        "mobilesdk_app_id": "1:924784679303:android:caa5f9866115461609db22",
        "android_client_info": {
          "package_name": "com.trimestre2.bottomnavigation"
        }
      },
      "oauth_client": [
        {
          "client_id": "924784679303-29ds8adknjmp1g3vstlrjunsdobpstqg.apps.googleusercontent.com",
          "client_type": 3
        }
      ],
      "api_key": [
        {
          "current_key": "AIzaSyBTpkZN_QAeNXyQbpjp1n6NitUaLvjgAjs"
        }
      ],
      "services": {
        "appinvite_service": {
          "other_platform_oauth_client": [
            {
              "client_id": "924784679303-29ds8adknjmp1g3vstlrjunsdobpstqg.apps.googleusercontent.com",
              "client_type": 3
            }
          ]
        }
      }
    }
  ],
  "configuration_version": "1"
}